trap/__init__.py
trap/_version.py
trap/associate.py
trap/cli.py
trap/io.py
trap/log.py
trap/post_processing.py
trap/run.py
trap/source_extraction.py
trap/visualize.py
trap-1.2.3.dist-info/licenses/LICENSE
trap-1.2.3.dist-info/METADATA
trap-1.2.3.dist-info/WHEEL
trap-1.2.3.dist-info/entry_points.txt
trap-1.2.3.dist-info/top_level.txt
trap-1.2.3.dist-info/RECORD
