Metadata-Version: 2.4
Name: trap
Version: 1.2.3
Summary: The Transients Pipeline (or 'TraP') is a Python based system for detecting and responding to transient and variable sources in a stream of astronomical images.
Author-email: Timo Millenaar <millenaar@astron.com>
License:                                  Apache License
Project-URL: homepage, https://git.astron.nl/RD/trap
Project-URL: repository, https://git.astron.nl/RD/trap
Keywords: trap,transients,astronomy,tkp
Classifier: Programming Language :: Python :: 3
Classifier: Programming Language :: Python :: 3.10
Classifier: Programming Language :: Python :: 3.11
Classifier: Programming Language :: Python :: 3.12
Classifier: Programming Language :: Python :: 3.13
Classifier: License :: OSI Approved :: Apache Software License
Classifier: Operating System :: OS Independent
License-File: LICENSE
Requires-Dist: radio-pyse==0.7.1
Requires-Dist: numba<0.62.0
Requires-Dist: numpy
Requires-Dist: pandas
Requires-Dist: sqlalchemy
Requires-Dist: psycopg2-binary
Requires-Dist: toml; python_version < "3.11"
Requires-Dist: dask[distributed]
Provides-Extra: doc
Requires-Dist: sphinx; extra == "doc"
Requires-Dist: sphinx_rtd_theme; extra == "doc"
Requires-Dist: sphinx-gallery; extra == "doc"
Requires-Dist: matplotlib; extra == "doc"
Provides-Extra: test
Requires-Dist: pytest; extra == "test"
Requires-Dist: pytest-cov; extra == "test"
Requires-Dist: pre-commit; extra == "test"
Requires-Dist: black; extra == "test"
Requires-Dist: isort; extra == "test"
Requires-Dist: mypy; extra == "test"
Requires-Dist: types-toml; extra == "test"
Provides-Extra: build
Requires-Dist: build; extra == "build"
Requires-Dist: setuptools-scm; extra == "build"
Requires-Dist: twine; extra == "build"
Provides-Extra: view
Requires-Dist: matplotlib; extra == "view"
Requires-Dist: pygfx; extra == "view"
Requires-Dist: glfw; extra == "view"
Requires-Dist: PyQt5; extra == "view"
Dynamic: license-file
